{"kind": "youtube#playlistListResponse", "etag": "op0Dt0dOTH6Ss3_RLtCXopc3g6A", "pageInfo": {"totalResults": 1, "resultsPerPage": 20}, "items": [{"kind": "youtube#playlist", "etag": "PK-pJUtI3Df9AIUCrlyucKA3Epw", "id": "PL99UH3EXlwttmXMpNBZXoZDMvk93ONxf7", "snippet": {"publishedAt": "2019-10-02T02:37:06Z", "channelId": "UC8th9Wc-YGKMYy2jPt_1sUw", "title": "조갑제", "description": "", "thumbnails": {"default": {"url": "https://i.ytimg.com/vi/auNocSPmvkA/default.jpg", "width": 120, "height": 90}, "medium": {"url": "https://i.ytimg.com/vi/auNocSPmvkA/mqdefault.jpg", "width": 320, "height": 180}, "high": {"url": "https://i.ytimg.com/vi/auNocSPmvkA/hqdefault.jpg", "width": 480, "height": 360}, "standard": {"url": "https://i.ytimg.com/vi/auNocSPmvkA/sddefault.jpg", "width": 640, "height": 480}}, "channelTitle": "홍동심tv", "localized": {"title": "조갑제", "description": ""}}, "contentDetails": {"itemCount": 18}}]}