{"kind": "youtube#playlistListResponse", "etag": "fmaHDflm3frgogJLFeDuqgM7lgY", "pageInfo": {"totalResults": 12, "resultsPerPage": 20}, "items": [{"kind": "youtube#playlist", "etag": "hO4JTa4VViMZNR64m_QAhedCs9k", "id": "PLaN3xBtVMok_nxU9C5USBI1geixH4wcfZ", "snippet": {"publishedAt": "2022-05-06T00:11:34Z", "channelId": "UCckoQzWfBa5l3EK9AcCpAhw", "title": "고양이에대한 기본 상식 모음", "description": "고양이에 대한 여러 신기한 상식에 관한 영상 모음 입니다.", "thumbnails": {"default": {"url": "https://i.ytimg.com/vi/ZtdZiBrh9Oc/default.jpg", "width": 120, "height": 90}, "medium": {"url": "https://i.ytimg.com/vi/ZtdZiBrh9Oc/mqdefault.jpg", "width": 320, "height": 180}, "high": {"url": "https://i.ytimg.com/vi/ZtdZiBrh9Oc/hqdefault.jpg", "width": 480, "height": 360}, "standard": {"url": "https://i.ytimg.com/vi/ZtdZiBrh9Oc/sddefault.jpg", "width": 640, "height": 480}, "maxres": {"url": "https://i.ytimg.com/vi/ZtdZiBrh9Oc/maxresdefault.jpg", "width": 1280, "height": 720}}, "channelTitle": "윤샘의 마이펫상담소-Pet Clinic", "localized": {"title": "고양이에대한 기본 상식 모음", "description": "고양이에 대한 여러 신기한 상식에 관한 영상 모음 입니다."}}, "contentDetails": {"itemCount": 56}}, {"kind": "youtube#playlist", "etag": "68EH6PEx0ACansgn41T8mEl2-IA", "id": "PLaN3xBtVMok8IxWKkksoqf5Rx7nZJLu-1", "snippet": {"publishedAt": "2022-05-06T00:11:23Z", "channelId": "UCckoQzWfBa5l3EK9AcCpAhw", "title": "고양이 행동학을 배워보자", "description": "고양이 행동학을 공부하고 싶으시면 하나한 영상 차분하게 보시면 많은 도움이 되실것 같습니다.", "thumbnails": {"default": {"url": "https://i.ytimg.com/vi/J9HgS9skNPQ/default.jpg", "width": 120, "height": 90}, "medium": {"url": "https://i.ytimg.com/vi/J9HgS9skNPQ/mqdefault.jpg", "width": 320, "height": 180}, "high": {"url": "https://i.ytimg.com/vi/J9HgS9skNPQ/hqdefault.jpg", "width": 480, "height": 360}, "standard": {"url": "https://i.ytimg.com/vi/J9HgS9skNPQ/sddefault.jpg", "width": 640, "height": 480}, "maxres": {"url": "https://i.ytimg.com/vi/J9HgS9skNPQ/maxresdefault.jpg", "width": 1280, "height": 720}}, "channelTitle": "윤샘의 마이펫상담소-Pet Clinic", "localized": {"title": "고양이 행동학을 배워보자", "description": "고양이 행동학을 공부하고 싶으시면 하나한 영상 차분하게 보시면 많은 도움이 되실것 같습니다."}}, "contentDetails": {"itemCount": 39}}, {"kind": "youtube#playlist", "etag": "jPNqPtR4bMNPo-nQS-l_WYDG0Xw", "id": "PLaN3xBtVMok-TvaBCl95C8G4HGuHlYPPd", "snippet": {"publishedAt": "2022-05-06T00:11:12Z", "channelId": "UCckoQzWfBa5l3EK9AcCpAhw", "title": "고양이 영양학을 배워보자", "description": "내 고양이 무얼 먹일지 어떤걸 먹일지 어떤 음식이 좋은건지에 대해 알고싶다면 시청해야할 영상들 입니다.", "thumbnails": {"default": {"url": "https://i.ytimg.com/vi/0Z_xvw5FMlc/default.jpg", "width": 120, "height": 90}, "medium": {"url": "https://i.ytimg.com/vi/0Z_xvw5FMlc/mqdefault.jpg", "width": 320, "height": 180}, "high": {"url": "https://i.ytimg.com/vi/0Z_xvw5FMlc/hqdefault.jpg", "width": 480, "height": 360}, "standard": {"url": "https://i.ytimg.com/vi/0Z_xvw5FMlc/sddefault.jpg", "width": 640, "height": 480}, "maxres": {"url": "https://i.ytimg.com/vi/0Z_xvw5FMlc/maxresdefault.jpg", "width": 1280, "height": 720}}, "channelTitle": "윤샘의 마이펫상담소-Pet Clinic", "localized": {"title": "고양이 영양학을 배워보자", "description": "내 고양이 무얼 먹일지 어떤걸 먹일지 어떤 음식이 좋은건지에 대해 알고싶다면 시청해야할 영상들 입니다."}}, "contentDetails": {"itemCount": 29}}, {"kind": "youtube#playlist", "etag": "RAigCJyvUDidEMwUBeDFTGju05E", "id": "PLaN3xBtVMok_OY2yJq8KCcZ-1RuGndhRT", "snippet": {"publishedAt": "2022-05-06T00:11:00Z", "channelId": "UCckoQzWfBa5l3EK9AcCpAhw", "title": "고양이 언어를 배워보자", "description": "고양이 언어를 배워볼수있는 영상 모음입니다.", "thumbnails": {"default": {"url": "https://i.ytimg.com/vi/DeJ-XmmrFc4/default.jpg", "width": 120, "height": 90}, "medium": {"url": "https://i.ytimg.com/vi/DeJ-XmmrFc4/mqdefault.jpg", "width": 320, "height": 180}, "high": {"url": "https://i.ytimg.com/vi/DeJ-XmmrFc4/hqdefault.jpg", "width": 480, "height": 360}, "standard": {"url": "https://i.ytimg.com/vi/DeJ-XmmrFc4/sddefault.jpg", "width": 640, "height": 480}, "maxres": {"url": "https://i.ytimg.com/vi/DeJ-XmmrFc4/maxresdefault.jpg", "width": 1280, "height": 720}}, "channelTitle": "윤샘의 마이펫상담소-Pet Clinic", "localized": {"title": "고양이 언어를 배워보자", "description": "고양이 언어를 배워볼수있는 영상 모음입니다."}}, "contentDetails": {"itemCount": 23}}, {"kind": "youtube#playlist", "etag": "NJv1MGLQEfyGtr2tg2B7uxOLZng", "id": "PLaN3xBtVMok95La8q-THFqc-LoeHqKt8H", "snippet": {"publishedAt": "2022-05-06T00:10:49Z", "channelId": "UCckoQzWfBa5l3EK9AcCpAhw", "title": "고양이 질병 사전", "description": "고양이의 질병에대한 여러 정보를 모은 영상입니다.", "thumbnails": {"default": {"url": "https://i.ytimg.com/vi/WkyEEnWOakU/default.jpg", "width": 120, "height": 90}, "medium": {"url": "https://i.ytimg.com/vi/WkyEEnWOakU/mqdefault.jpg", "width": 320, "height": 180}, "high": {"url": "https://i.ytimg.com/vi/WkyEEnWOakU/hqdefault.jpg", "width": 480, "height": 360}, "standard": {"url": "https://i.ytimg.com/vi/WkyEEnWOakU/sddefault.jpg", "width": 640, "height": 480}, "maxres": {"url": "https://i.ytimg.com/vi/WkyEEnWOakU/maxresdefault.jpg", "width": 1280, "height": 720}}, "channelTitle": "윤샘의 마이펫상담소-Pet Clinic", "localized": {"title": "고양이 질병 사전", "description": "고양이의 질병에대한 여러 정보를 모은 영상입니다."}}, "contentDetails": {"itemCount": 55}}, {"kind": "youtube#playlist", "etag": "AEtHX9uWJbm7-Gb3DfwYJhF4Kdk", "id": "PLaN3xBtVMok_M9cAE4pRrfdj7FUgeMj0j", "snippet": {"publishedAt": "2022-05-06T00:10:34Z", "channelId": "UCckoQzWfBa5l3EK9AcCpAhw", "title": "고양이를 키우신다면 구입해야할 용품 소개", "description": "추천하는 용품들의 소개와 설명영상 입니다. 광고 영상도 섞여있으니 잘 구분해서 보시면 구입에 도움이 되실것 입니다. 광고라도 좋은것 아니면 추천을 안했습니다.", "thumbnails": {"default": {"url": "https://i.ytimg.com/vi/ZU9ks15iJzg/default.jpg", "width": 120, "height": 90}, "medium": {"url": "https://i.ytimg.com/vi/ZU9ks15iJzg/mqdefault.jpg", "width": 320, "height": 180}, "high": {"url": "https://i.ytimg.com/vi/ZU9ks15iJzg/hqdefault.jpg", "width": 480, "height": 360}, "standard": {"url": "https://i.ytimg.com/vi/ZU9ks15iJzg/sddefault.jpg", "width": 640, "height": 480}, "maxres": {"url": "https://i.ytimg.com/vi/ZU9ks15iJzg/maxresdefault.jpg", "width": 1280, "height": 720}}, "channelTitle": "윤샘의 마이펫상담소-Pet Clinic", "localized": {"title": "고양이를 키우신다면 구입해야할 용품 소개", "description": "추천하는 용품들의 소개와 설명영상 입니다. 광고 영상도 섞여있으니 잘 구분해서 보시면 구입에 도움이 되실것 입니다. 광고라도 좋은것 아니면 추천을 안했습니다."}}, "contentDetails": {"itemCount": 21}}, {"kind": "youtube#playlist", "etag": "M8QT3wncS0xivZHmLT0kMGrNluc", "id": "PLaN3xBtVMok9c_oZP2TL66zeaepmK22YH", "snippet": {"publishedAt": "2022-05-06T00:10:19Z", "channelId": "UCckoQzWfBa5l3EK9AcCpAhw", "title": "길냥이를 입양했다면 봐야할 영상", "description": "길냥이를 입양했다면 봐야할 길냥이 특징에 관련된 영상 입니다.", "thumbnails": {"default": {"url": "https://i.ytimg.com/vi/MacE49O_O8M/default.jpg", "width": 120, "height": 90}, "medium": {"url": "https://i.ytimg.com/vi/MacE49O_O8M/mqdefault.jpg", "width": 320, "height": 180}, "high": {"url": "https://i.ytimg.com/vi/MacE49O_O8M/hqdefault.jpg", "width": 480, "height": 360}, "standard": {"url": "https://i.ytimg.com/vi/MacE49O_O8M/sddefault.jpg", "width": 640, "height": 480}, "maxres": {"url": "https://i.ytimg.com/vi/MacE49O_O8M/maxresdefault.jpg", "width": 1280, "height": 720}}, "channelTitle": "윤샘의 마이펫상담소-Pet Clinic", "localized": {"title": "길냥이를 입양했다면 봐야할 영상", "description": "길냥이를 입양했다면 봐야할 길냥이 특징에 관련된 영상 입니다."}}, "contentDetails": {"itemCount": 13}}, {"kind": "youtube#playlist", "etag": "fZ9VQ1phHft4508-bdF0n3qrfnk", "id": "PLaN3xBtVMok8kG27sDsG6TMznJkEFjyfw", "snippet": {"publishedAt": "2022-05-06T00:10:06Z", "channelId": "UCckoQzWfBa5l3EK9AcCpAhw", "title": "고양이를 조금 키워보신분들도 봐야할 영상", "description": "고양이를 조금 키워보신분들도 알고계셔야할 정보를 담았습니다.", "thumbnails": {"default": {"url": "https://i.ytimg.com/vi/J9HgS9skNPQ/default.jpg", "width": 120, "height": 90}, "medium": {"url": "https://i.ytimg.com/vi/J9HgS9skNPQ/mqdefault.jpg", "width": 320, "height": 180}, "high": {"url": "https://i.ytimg.com/vi/J9HgS9skNPQ/hqdefault.jpg", "width": 480, "height": 360}, "standard": {"url": "https://i.ytimg.com/vi/J9HgS9skNPQ/sddefault.jpg", "width": 640, "height": 480}, "maxres": {"url": "https://i.ytimg.com/vi/J9HgS9skNPQ/maxresdefault.jpg", "width": 1280, "height": 720}}, "channelTitle": "윤샘의 마이펫상담소-Pet Clinic", "localized": {"title": "고양이를 조금 키워보신분들도 봐야할 영상", "description": "고양이를 조금 키워보신분들도 알고계셔야할 정보를 담았습니다."}}, "contentDetails": {"itemCount": 77}}, {"kind": "youtube#playlist", "etag": "m09QfzRSuKUd5M8oX_QtNvWeBi4", "id": "PLaN3xBtVMok-3ogTecaqWwVIj8PeznK1s", "snippet": {"publishedAt": "2022-05-06T00:09:49Z", "channelId": "UCckoQzWfBa5l3EK9AcCpAhw", "title": "고양이를 처음 키우신다면 봐야할 영상", "description": "아직 고양이가 익숙하지 않으시다면 필수로 시청해야하는 영상들 입니다.", "thumbnails": {"default": {"url": "https://i.ytimg.com/vi/hvNqM2Rtoc0/default.jpg", "width": 120, "height": 90}, "medium": {"url": "https://i.ytimg.com/vi/hvNqM2Rtoc0/mqdefault.jpg", "width": 320, "height": 180}, "high": {"url": "https://i.ytimg.com/vi/hvNqM2Rtoc0/hqdefault.jpg", "width": 480, "height": 360}, "standard": {"url": "https://i.ytimg.com/vi/hvNqM2Rtoc0/sddefault.jpg", "width": 640, "height": 480}, "maxres": {"url": "https://i.ytimg.com/vi/hvNqM2Rtoc0/maxresdefault.jpg", "width": 1280, "height": 720}}, "channelTitle": "윤샘의 마이펫상담소-Pet Clinic", "localized": {"title": "고양이를 처음 키우신다면 봐야할 영상", "description": "아직 고양이가 익숙하지 않으시다면 필수로 시청해야하는 영상들 입니다."}}, "contentDetails": {"itemCount": 106}}, {"kind": "youtube#playlist", "etag": "eTZLl9n4GGeocV6EI0XnxQxIGgM", "id": "PLaN3xBtVMok_skuIabK8IXqAtSerAZw5Z", "snippet": {"publishedAt": "2021-04-21T00:15:10Z", "channelId": "UCckoQzWfBa5l3EK9AcCpAhw", "title": "라이브 상담소 요약본", "description": "격주로 진행하는 라이브 방송의 정리 요약본입니다. 요약본이 나오면 오리지널 방송본은 유료회원 전용으로 전환 합니다.", "thumbnails": {"default": {"url": "https://i.ytimg.com/vi/g1UuQ-rBZsE/default.jpg", "width": 120, "height": 90}, "medium": {"url": "https://i.ytimg.com/vi/g1UuQ-rBZsE/mqdefault.jpg", "width": 320, "height": 180}, "high": {"url": "https://i.ytimg.com/vi/g1UuQ-rBZsE/hqdefault.jpg", "width": 480, "height": 360}, "standard": {"url": "https://i.ytimg.com/vi/g1UuQ-rBZsE/sddefault.jpg", "width": 640, "height": 480}, "maxres": {"url": "https://i.ytimg.com/vi/g1UuQ-rBZsE/maxresdefault.jpg", "width": 1280, "height": 720}}, "channelTitle": "윤샘의 마이펫상담소-Pet Clinic", "localized": {"title": "라이브 상담소 요약본", "description": "격주로 진행하는 라이브 방송의 정리 요약본입니다. 요약본이 나오면 오리지널 방송본은 유료회원 전용으로 전환 합니다."}}, "contentDetails": {"itemCount": 57}}, {"kind": "youtube#playlist", "etag": "kpjhocMH2yYqkIxvOOE-ACL-plU", "id": "PLaN3xBtVMok9E0eyvQ17qXMEofOmQAi3w", "snippet": {"publishedAt": "2019-12-05T23:43:25Z", "channelId": "UCckoQzWfBa5l3EK9AcCpAhw", "title": "멤버쉽(유료) 회원 전용 영상", "description": "라이브 방송 모음 입니다.  제 개인적인 신상과 썰이 난무한 방송이라 멤버쉽 전용으로 제한 하였습니다.  라이브 방송후 요약 영상을 만들어 일반공개하고 있으니 유료 회원이 아니신 분들은 잘 정리된 요약영상을 보시면 됩니다.", "thumbnails": {"default": {"url": "https://i.ytimg.com/vi/ATq_XQuXQw4/default.jpg", "width": 120, "height": 90}, "medium": {"url": "https://i.ytimg.com/vi/ATq_XQuXQw4/mqdefault.jpg", "width": 320, "height": 180}, "high": {"url": "https://i.ytimg.com/vi/ATq_XQuXQw4/hqdefault.jpg", "width": 480, "height": 360}, "standard": {"url": "https://i.ytimg.com/vi/ATq_XQuXQw4/sddefault.jpg", "width": 640, "height": 480}, "maxres": {"url": "https://i.ytimg.com/vi/ATq_XQuXQw4/maxresdefault.jpg", "width": 1280, "height": 720}}, "channelTitle": "윤샘의 마이펫상담소-Pet Clinic", "localized": {"title": "멤버쉽(유료) 회원 전용 영상", "description": "라이브 방송 모음 입니다.  제 개인적인 신상과 썰이 난무한 방송이라 멤버쉽 전용으로 제한 하였습니다.  라이브 방송후 요약 영상을 만들어 일반공개하고 있으니 유료 회원이 아니신 분들은 잘 정리된 요약영상을 보시면 됩니다."}}, "contentDetails": {"itemCount": 104}}, {"kind": "youtube#playlist", "etag": "AdDxXOV6OCU7gYp--JwM9pQD4FM", "id": "PLaN3xBtVMok9VaB-KTc-fBFZlogAJ47nD", "snippet": {"publishedAt": "2019-10-04T23:30:16Z", "channelId": "UCckoQzWfBa5l3EK9AcCpAhw", "title": "집사의 삶의질을 위한 영상모음", "description": "고양이를 키우는 여러분들을 위한 영상입니다.", "thumbnails": {"default": {"url": "https://i.ytimg.com/vi/BOo3RVEJ0XM/default.jpg", "width": 120, "height": 90}, "medium": {"url": "https://i.ytimg.com/vi/BOo3RVEJ0XM/mqdefault.jpg", "width": 320, "height": 180}, "high": {"url": "https://i.ytimg.com/vi/BOo3RVEJ0XM/hqdefault.jpg", "width": 480, "height": 360}, "standard": {"url": "https://i.ytimg.com/vi/BOo3RVEJ0XM/sddefault.jpg", "width": 640, "height": 480}, "maxres": {"url": "https://i.ytimg.com/vi/BOo3RVEJ0XM/maxresdefault.jpg", "width": 1280, "height": 720}}, "channelTitle": "윤샘의 마이펫상담소-Pet Clinic", "localized": {"title": "집사의 삶의질을 위한 영상모음", "description": "고양이를 키우는 여러분들을 위한 영상입니다."}}, "contentDetails": {"itemCount": 61}}]}