{"밈 영상": {"kind": "youtube#playlistItemListResponse", "etag": "Fodk9Te-BN4z8rFL2dHJhrmu-g8", "items": [{"kind": "youtube#playlistItem", "etag": "o3G3lMJeK_fmvKkXDqC8N_waiKQ", "id": "UExpcFp4cDRZZ1YwcUdwQ1M0eHhyLUEzVXIwTWN3Mm8wNC41NkI0NEY2RDEwNTU3Q0M2", "snippet": {"publishedAt": "2023-06-11T16:19:47Z", "channelId": "UCtojzusGJRtRzD6vAx2DBhQ", "title": "marine waffle meme", "description": "번역 연습이라 오역이 있을 수 있습니다. 고쳐야 할 부분 알려주신다면 감사하겠습니다.\n\n댓글을 써주시는 것은 감사하지만 선을 넘는 댓글이나 해당 스트리머를 비방하는 말은 삼가해주시기 바랍니다. 선은 선장님보다 안쪽에 있습니다. 경우에 따라서는 댓글을 차단하거나 삭제할 수 있습니다.\n이 채널에서는 빨간약을 다루지 않습니다. 언급은 자제해주시기 바랍니다.\n(※빨간약 : 버튜버의 전생이나 실제 인물에 관한 내용)\n\n원본\n▶ 제목: \n【Getting Over It】辛くないよ…Mだから。【ホロライブ/宝鐘マリン】\nI'M H O R N Y【hololive/houshou marine & Gawr Gura】\n▶ 링크: \nhttps://www.youtube.com/watch?v=i65IR6Ltc2E\nhttps://www.youtube.com/watch?v=Tmm8ig9P_Ak\n\n아웃트로\n▶ 제목: キミたち…おいで♡【ホロライブ/宝鐘マリン】\n▶ 링크: https://youtu.be/bXW0smuBT8w\n\n마린 선장 채널\n▶ https://www.youtube.com/channel/UCCzUftO8KOVkV4wQG1vkUvg\n\n자막바\n▶ 제작: 유시아 .YUUSHA04\n▶ 링크: https://www.youtube.com/channel/UCilHGRioGk-uNtKOTJPt8XQ/community?lb=UgkxWRlwU45zWXCasKKs3lNijjx-zWo_kXAs\n\n사용폰트\n메이플 스토리 - 넥슨\nMapo홍대프리덤 - 서울시 마포구\n솔뫼 김대건체 - 써밋 디자인\n\n#버튜버 #마린 #호쇼마린 #宝鐘の一味 #マリン航海記 #shorts", "thumbnails": {"default": {"url": "https://i.ytimg.com/vi/xZeBUHlRBJE/default.jpg", "width": 120, "height": 90}, "medium": {"url": "https://i.ytimg.com/vi/xZeBUHlRBJE/mqdefault.jpg", "width": 320, "height": 180}, "high": {"url": "https://i.ytimg.com/vi/xZeBUHlRBJE/hqdefault.jpg", "width": 480, "height": 360}, "standard": {"url": "https://i.ytimg.com/vi/xZeBUHlRBJE/sddefault.jpg", "width": 640, "height": 480}, "maxres": {"url": "https://i.ytimg.com/vi/xZeBUHlRBJE/maxresdefault.jpg", "width": 1280, "height": 720}}, "channelTitle": "게으른 이치미 [호쇼 마린 키리누키 ch]", "playlistId": "PLipZxp4YgV0qGpCS4xxr-A3Ur0Mcw2o04", "position": 0, "resourceId": {"kind": "youtube#video", "videoId": "xZeBUHlRBJE"}, "videoOwnerChannelTitle": "게으른 이치미 [호쇼 마린 키리누키 ch]", "videoOwnerChannelId": "UCtojzusGJRtRzD6vAx2DBhQ"}, "contentDetails": {"videoId": "xZeBUHlRBJE", "videoPublishedAt": "2023-06-11T16:19:47Z"}}], "pageInfo": {"totalResults": 1, "resultsPerPage": 15}}, "키리누키 모음": {"kind": "youtube#playlistItemListResponse", "etag": "ARtAig9CUG2PmtOYehJVBMawLp8", "items": [{"kind": "youtube#playlistItem", "etag": "NyK3CurdQ7C4VeWaMb7oYEurhS8", "id": "UExpcFp4cDRZZ1YwcG1abkdTYWRYSXIzN0hIbWp3Q2UtWS41NkI0NEY2RDEwNTU3Q0M2", "snippet": {"publishedAt": "2022-12-30T07:39:51Z", "channelId": "UCtojzusGJRtRzD6vAx2DBhQ", "title": "2022년 개인적으로 뽑은 하이라이트 (업로드한 영상중)", "description": "넣고 보니까 놓친 것이 있어서 아쉽네요 2023에는 더 열심히 하겠습니다\n\n번역 연습이라 오역이 있을 수 있습니다. 고쳐야 할 부분 알려주신다면 감사하겠습니다.\n\n댓글을 써주시는 것은 감사하지만 선을 넘는 댓글이나 해당 스트리머를 비방하는 말은 삼가해주시기 바랍니다. 선은 선장님보다 안쪽에 있습니다. 경우에 따라서는 댓글을 차단하거나 삭제할 수 있습니다.\n이 채널에서는 빨간약을 다루지 않습니다. 언급은 자제해주시기 바랍니다.\n(※빨간약 : 버튜버의 전생이나 실제 인물에 관한 내용)\n\n원본\n▶ 제목: \n【#りっちしょこら】今回のゲストはマリン様⚡ルイ様とビーフストロガノフ作る！【ホロライブ/癒月ちょこ/鷹嶺ルイ/宝鐘マリン】\n【#ホロGarticPhone】ホロの画伯たちでお絵かき伝言やるぞやるぞ【ホロライブ/宝鐘マリン】\n【かなしい】えっ！？洞窟間に合わないんですか！？代わりに全員で人狼！？できるのかい！？【#ARK廃人村人狼】\n【オフコラボ】こより…泊まっていけよ…【ホロライブ/宝鐘マリン・博衣こより】\n【1-2-Switch】応援ありがとう！まるヤマよ 永遠に！編【 ホロライブ #まるヤマ駅前】\n【マリンはもう運動から逃げない】Nintendo Switch Sports【ホロライブ/宝鐘マリン】\n【#ぺこマリ1ブロック】最終回！来年もぺこマリあるよな？ぺこら…【ホロライブ/宝鐘マリン・兎田ぺこら】\n【#マリフレオフ】絆の歌枠【ホロライブ/宝鐘マリン】\n【アソビ大全】1時間で鷹嶺ルイをぼこぼこにして泣かす【ホロライブ/宝鐘マリン・鷹嶺ルイ】\n【登録者200万人！】歌ったり語ったりする【ホロライブ/宝鐘マリン】\n【メンバーシップ限定】ねむねむお話会【ホロライブ/宝鐘マリン】\n【3D LIVE!!!】3D新衣装お披露目!! ゲストと歌って踊って生誕祭♪♪♪【hololive/宝鐘マリン】\n【誕生日カウントダウン】17歳4週目、見てほしいものがあります。【ホロライブ/宝鐘マリン】\n【#ホロ鯖夏祭り】夏祭り2022！！！Summer Festival YEAHHHH！！【天音かなた/ホロライブ】\n【みんなのリズム天国】ふたりの地獄リズム【ホロライブ/宝鐘マリン】\n【HoloCure】新キャラ ガチャ祭開催!!!新ステージいきます!!!【ホロライブ/宝鐘マリン】\n 【#Reine2ndMEPtember】REINE MERAKETING ACADEMY!!! WHO WILL CALL?【Pavolia Reine/hololiveID 2nd gen】\n【イラストメイキング】合作！！おえかき得意清楚美少女★【ホロライブ/宝鐘マリン・夏色まつり】\n【一か月ぶり】イラスト付きお休みレポート雑談【ホロライブ/宝鐘マリン】\n【地獄銭湯】怖くて風呂で目を瞑れないタイプのマリン銭湯【ホロライブ/宝鐘マリン】\n【歌枠】アニソンKARAOKEタイム♪【ホロライブ/宝鐘マリン】\n【＃ぺこマリ】オフコラボぺこマリゲーム対決！！！！！！！！！！ぺこ！【ホロライブ/兎田ぺこら】\n【Minecraft】白組前半担当のみんなで運動会の練習！！！【天音かなた/ホロライブ】\n【ゲスト多数！新髪型お披露目！】昭和老人会♪宝鐘マリン3周年記念歌謡祭【hololive/宝鐘マリン】\n【ラミィ生誕記念2022】今年も好き放題やります！100万円晩酌【 #やかまし100万円飲み会 /ホロライブ】\n【#ホロAmongUs】ホロライブスキンで遊ぶぞ！信用できる船長です【ホロライブ/宝鐘マリン】\n【#ホロAmongUs】突発コラボ！宇宙でわちゃわちゃ！！【博衣こより視点/ホロライブ】\n≪NEWLY FRIEND GAME≫ A pirate and a rat\n【モンハンライズ】優雅美麗姉流狩術【#ホロファンお姉さん組】\n【オフコラボ♡】取り直しました！この組み合わせどうなる⁉紅サンタ達のプチクリスマスパーティー。#おにたかマリ　【百鬼あやめ/宝鐘マリン/鷹嶺ルイ/ホロライブ】\n\n▶ 링크: \nhttps://www.youtube.com/watch?v=YeiJnvJWVgw\nhttps://www.youtube.com/watch?v=0SfUNfAg1cM\nhttps://www.youtube.com/watch?v=ZL287oa1Fr0\nhttps://youtu.be/ERGC4xQYjvE\n https://www.youtube.com/watch?v=vZ4GjrklW_g\nhttps://www.youtube.com/watch?v=m6xJ8yzcdUo\nhttps://www.youtube.com/watch?v=6n1YGPPmSFk\nhttps://www.youtube.com/watch?v=NswPv5U7N-Y\nhttps://www.youtube.com/watch?v=bZmRte48iGo\nhttps://www.youtube.com/watch?v=IsKfSOipdoA\nhttps://youtu.be/waBnG141kqE\nhttps://www.youtube.com/watch?v=wF_VmniNI2I\nhttps://youtu.be/u2mQNC-NT_c\nhttps://www.youtube.com/watch?v=Da7SfX5Xr4U\nhttps://www.youtube.com/watch?v=UY9MNJwmcWI\nhttps://www.youtube.com/watch?v=de4XvSRu8DI\nhttps://www.youtube.com/watch?v=Wgb3Az8w-Pw\nhttps://www.youtube.com/watch?v=JNOHZMzgbrM\nhttps://www.youtube.com/watch?v=lYN1JQ2HlmI\nhttps://www.youtube.com/watch?v=kNX-wQTvsws\nhttps://www.youtube.com/watch?v=-niT_EG6qd4\nhttps://youtu.be/fKW6F3GhMcQ\nhttps://youtu.be/9oBKOIMqJ0U\nhttps://youtu.be/3LaDuoHDC_g\nhttps://www.youtube.com/watch?v=hzmimWcN34Q\nhttps://www.youtube.com/watch?v=AbERn21JSL4\nhttps://www.youtube.com/watch?v=onkfRfowI_A\nhttps://youtu.be/ka9U5Gm0gO0\nhttps://youtu.be/6o0u_3hAzL0\nhttps://youtu.be/jWb_jsER5ss\n\n마린 선장 채널\n▶ https://www.youtube.com/channel/UCCzUftO8KOVkV4wQG1vkUvg\n\n자막바\n▶ 제작: 유시아 .YUUSHA04\n▶ 링크: https://www.youtube.com/channel/UCilHGRioGk-uNtKOTJPt8XQ/community?lb=UgkxWRlwU45zWXCasKKs3lNijjx-zWo_kXAs\n\n#버튜버 #마린 #호쇼마린 #宝鐘の一味 #マリン航海記", "thumbnails": {"default": {"url": "https://i.ytimg.com/vi/tSbqC4-EYgw/default.jpg", "width": 120, "height": 90}, "medium": {"url": "https://i.ytimg.com/vi/tSbqC4-EYgw/mqdefault.jpg", "width": 320, "height": 180}, "high": {"url": "https://i.ytimg.com/vi/tSbqC4-EYgw/hqdefault.jpg", "width": 480, "height": 360}, "standard": {"url": "https://i.ytimg.com/vi/tSbqC4-EYgw/sddefault.jpg", "width": 640, "height": 480}, "maxres": {"url": "https://i.ytimg.com/vi/tSbqC4-EYgw/maxresdefault.jpg", "width": 1280, "height": 720}}, "channelTitle": "게으른 이치미 [호쇼 마린 키리누키 ch]", "playlistId": "PLipZxp4YgV0pmZnGSadXIr37HHmjwCe-Y", "position": 0, "resourceId": {"kind": "youtube#video", "videoId": "tSbqC4-EYgw"}, "videoOwnerChannelTitle": "게으른 이치미 [호쇼 마린 키리누키 ch]", "videoOwnerChannelId": "UCtojzusGJRtRzD6vAx2DBhQ"}, "contentDetails": {"videoId": "tSbqC4-EYgw", "videoPublishedAt": "2022-12-30T08:02:37Z"}}, {"kind": "youtube#playlistItem", "etag": "rd6LlmwQ0UUl_xULHilSXsKa_3E", "id": "UExpcFp4cDRZZ1YwcG1abkdTYWRYSXIzN0hIbWp3Q2UtWS4yODlGNEE0NkRGMEEzMEQy", "snippet": {"publishedAt": "2023-01-02T14:54:55Z", "channelId": "UCtojzusGJRtRzD6vAx2DBhQ", "title": "예술을 너무 잘아는 선장님의 포켓몬들", "description": "번역 연습이라 오역이 있을 수 있습니다. 고쳐야 할 부분 알려주신다면 감사하겠습니다.\n\n댓글을 써주시는 것은 감사하지만 선을 넘는 댓글이나 해당 스트리머를 비방하는 말은 삼가해주시기 바랍니다. 선은 선장님보다 안쪽에 있습니다. 경우에 따라서는 댓글을 차단하거나 삭제할 수 있습니다.\n이 채널에서는 빨간약을 다루지 않습니다. 언급은 자제해주시기 바랍니다.\n(※빨간약 : 버튜버의 전생이나 실제 인물에 관한 내용)\n\n원본\n▶ 제목: 【ポケモンSV】視聴者参加型ゆびをふる対決！！【ホロライブ/宝鐘マリン】\n▶ 링크: https://www.youtube.com/watch?v=9co_uamorL4\n\n아웃트로\n▶ 제목: 【MV】Happiness World【宝鐘マリン/白上フブキ】\n▶ 링크: https://youtu.be/OpveB76DTZk\n\n마린 선장 채널\n▶ https://www.youtube.com/channel/UCCzUftO8KOVkV4wQG1vkUvg\n\n자막바\n▶ 제작: 유시아 .YUUSHA04\n▶ 링크: https://www.youtube.com/channel/UCilHGRioGk-uNtKOTJPt8XQ/community?lb=UgkxWRlwU45zWXCasKKs3lNijjx-zWo_kXAs\n\n#버튜버 #마린 #호쇼마린 #宝鐘の一味 #マリン航海記", "thumbnails": {"default": {"url": "https://i.ytimg.com/vi/cxa8Z1odzTs/default.jpg", "width": 120, "height": 90}, "medium": {"url": "https://i.ytimg.com/vi/cxa8Z1odzTs/mqdefault.jpg", "width": 320, "height": 180}, "high": {"url": "https://i.ytimg.com/vi/cxa8Z1odzTs/hqdefault.jpg", "width": 480, "height": 360}, "standard": {"url": "https://i.ytimg.com/vi/cxa8Z1odzTs/sddefault.jpg", "width": 640, "height": 480}, "maxres": {"url": "https://i.ytimg.com/vi/cxa8Z1odzTs/maxresdefault.jpg", "width": 1280, "height": 720}}, "channelTitle": "게으른 이치미 [호쇼 마린 키리누키 ch]", "playlistId": "PLipZxp4YgV0pmZnGSadXIr37HHmjwCe-Y", "position": 1, "resourceId": {"kind": "youtube#video", "videoId": "cxa8Z1odzTs"}, "videoOwnerChannelTitle": "게으른 이치미 [호쇼 마린 키리누키 ch]", "videoOwnerChannelId": "UCtojzusGJRtRzD6vAx2DBhQ"}, "contentDetails": {"videoId": "cxa8Z1odzTs", "videoPublishedAt": "2023-01-02T14:55:30Z"}}, {"kind": "youtube#playlistItem", "etag": "dcEVuEqJQxhVe9fmoiakMGLpVdo", "id": "UExpcFp4cDRZZ1YwcG1abkdTYWRYSXIzN0hIbWp3Q2UtWS4wMTcyMDhGQUE4NTIzM0Y5", "snippet": {"publishedAt": "2023-01-09T14:35:31Z", "channelId": "UCtojzusGJRtRzD6vAx2DBhQ", "title": "선장님이 혼자 해외여행을 가게 될 때를 대비하는 키아라의 영어수업", "description": "번역 연습이라 오역이 있을 수 있습니다. 고쳐야 할 부분 알려주신다면 감사하겠습니다.\n\n댓글을 써주시는 것은 감사하지만 선을 넘는 댓글이나 해당 스트리머를 비방하는 말은 삼가해주시기 바랍니다. 선은 선장님보다 안쪽에 있습니다. 경우에 따라서는 댓글을 차단하거나 삭제할 수 있습니다.\n이 채널에서는 빨간약을 다루지 않습니다. 언급은 자제해주시기 바랍니다.\n(※빨간약 : 버튜버의 전생이나 실제 인물에 관한 내용)\n\n원본\n▶ 제목: キアラ…welcome to underground【ホロライブ/宝鐘マリン・小鳥遊キアラ】\n▶ 링크: https://www.youtube.com/watch?v=cwvxRk_3qHQ\n\n아웃트로\n▶ 제목: 【MV】Happiness World【宝鐘マリン/白上フブキ】\n▶ 링크: https://youtu.be/OpveB76DTZk\n\n마린 선장 채널\n▶ https://www.youtube.com/channel/UCCzUftO8KOVkV4wQG1vkUvg\n\n자막바\n▶ 제작: 유시아 .YUUSHA04\n▶ 링크: https://www.youtube.com/channel/UCilHGRioGk-uNtKOTJPt8XQ/community?lb=UgkxWRlwU45zWXCasKKs3lNijjx-zWo_kXAs\n\n#버튜버 #마린 #호쇼마린 #宝鐘の一味 #マリン航海記", "thumbnails": {"default": {"url": "https://i.ytimg.com/vi/cQyvdvLdW_I/default.jpg", "width": 120, "height": 90}, "medium": {"url": "https://i.ytimg.com/vi/cQyvdvLdW_I/mqdefault.jpg", "width": 320, "height": 180}, "high": {"url": "https://i.ytimg.com/vi/cQyvdvLdW_I/hqdefault.jpg", "width": 480, "height": 360}, "standard": {"url": "https://i.ytimg.com/vi/cQyvdvLdW_I/sddefault.jpg", "width": 640, "height": 480}, "maxres": {"url": "https://i.ytimg.com/vi/cQyvdvLdW_I/maxresdefault.jpg", "width": 1280, "height": 720}}, "channelTitle": "게으른 이치미 [호쇼 마린 키리누키 ch]", "playlistId": "PLipZxp4YgV0pmZnGSadXIr37HHmjwCe-Y", "position": 2, "resourceId": {"kind": "youtube#video", "videoId": "cQyvdvLdW_I"}, "videoOwnerChannelTitle": "게으른 이치미 [호쇼 마린 키리누키 ch]", "videoOwnerChannelId": "UCtojzusGJRtRzD6vAx2DBhQ"}, "contentDetails": {"videoId": "cQyvdvLdW_I", "videoPublishedAt": "2023-01-09T14:36:18Z"}}, {"kind": "youtube#playlistItem", "etag": "r5XoC6EVk8ur2nzhSIO680ZKcx0", "id": "UExpcFp4cDRZZ1YwcG1abkdTYWRYSXIzN0hIbWp3Q2UtWS41MjE1MkI0OTQ2QzJGNzNG", "snippet": {"publishedAt": "2023-02-14T10:46:11Z", "channelId": "UCtojzusGJRtRzD6vAx2DBhQ", "title": "아야메가 많이 나오니까 아쿠아 엄마 관두고 아야메의 엄마가 되겠습니다", "description": "번역 연습이라 오역이 있을 수 있습니다. 고쳐야 할 부분 알려주신다면 감사하겠습니다.\n\n댓글을 써주시는 것은 감사하지만 선을 넘는 댓글이나 해당 스트리머를 비방하는 말은 삼가해주시기 바랍니다. 선은 선장님보다 안쪽에 있습니다. 경우에 따라서는 댓글을 차단하거나 삭제할 수 있습니다.\n이 채널에서는 빨간약을 다루지 않습니다. 언급은 자제해주시기 바랍니다.\n(※빨간약 : 버튜버의 전생이나 실제 인물에 관한 내용)\n\n원본\n▶ 제목: 【HoloCure】ガチャしまくり！！！ホロキュア1期生＆二期生実装！娘を生む。【ホロライブ/宝鐘マリン】\n▶ 링크: https://www.youtube.com/watch?v=PAZSZNq0ePA\n\n아웃트로\n▶ 제목: マリン船長が可愛いだけの動画【hololive/宝鐘マリン】\n▶ 링크: https://www.youtube.com/watch?v=lViEcNT8snc\n\n마린 선장 채널\n▶ https://www.youtube.com/channel/UCCzUftO8KOVkV4wQG1vkUvg\n\n자막바\n▶ 제작: 유시아 .YUUSHA04\n▶ 링크: https://www.youtube.com/channel/UCilHGRioGk-uNtKOTJPt8XQ/community?lb=UgkxWRlwU45zWXCasKKs3lNijjx-zWo_kXAs\n\n사용폰트\n메이플 스토리 - 넥슨\nMapo홍대프리덤 - 서울시 마포구\n솔뫼 김대건체 - 써밋 디자인\n\n#버튜버 #마린 #호쇼마린 #宝鐘の一味 #マリン航海記", "thumbnails": {"default": {"url": "https://i.ytimg.com/vi/83HwrXiC7aY/default.jpg", "width": 120, "height": 90}, "medium": {"url": "https://i.ytimg.com/vi/83HwrXiC7aY/mqdefault.jpg", "width": 320, "height": 180}, "high": {"url": "https://i.ytimg.com/vi/83HwrXiC7aY/hqdefault.jpg", "width": 480, "height": 360}, "standard": {"url": "https://i.ytimg.com/vi/83HwrXiC7aY/sddefault.jpg", "width": 640, "height": 480}, "maxres": {"url": "https://i.ytimg.com/vi/83HwrXiC7aY/maxresdefault.jpg", "width": 1280, "height": 720}}, "channelTitle": "게으른 이치미 [호쇼 마린 키리누키 ch]", "playlistId": "PLipZxp4YgV0pmZnGSadXIr37HHmjwCe-Y", "position": 3, "resourceId": {"kind": "youtube#video", "videoId": "83HwrXiC7aY"}, "videoOwnerChannelTitle": "게으른 이치미 [호쇼 마린 키리누키 ch]", "videoOwnerChannelId": "UCtojzusGJRtRzD6vAx2DBhQ"}, "contentDetails": {"videoId": "83HwrXiC7aY", "videoPublishedAt": "2023-02-14T10:49:14Z"}}], "pageInfo": {"totalResults": 4, "resultsPerPage": 15}}, "마린 키리누키": {"kind": "youtube#playlistItemListResponse", "etag": "f1lJsHSI_6Gq27bck4y_Io0ikXs", "nextPageToken": "EAAaKVBUOkNBOGlFRVJCUVRVMU1VTkdOekF3T0RRMFF6TW9BVENTZ19DbkJn", "items": [{"kind": "youtube#playlistItem", "etag": "O7wDrLXKqeDHKsAfS_v65Hryhwg", "id": "UExpcFp4cDRZZ1YwcngwN3dqd3JJOEhZc3hJbnFkVHJLOC41NkI0NEY2RDEwNTU3Q0M2", "snippet": {"publishedAt": "2021-11-22T08:06:49Z", "channelId": "UCtojzusGJRtRzD6vAx2DBhQ", "title": "Private video", "description": "This video is private.", "thumbnails": {}, "channelTitle": "게으른 이치미 [호쇼 마린 키리누키 ch]", "playlistId": "PLipZxp4YgV0rx07wjwrI8HYsxInqdTrK8", "position": 0, "resourceId": {"kind": "youtube#video", "videoId": "wIt634Uqm4w"}}, "contentDetails": {"videoId": "wIt634Uqm4w"}}, {"kind": "youtube#playlistItem", "etag": "aZdi_SdlU8aQ-cKB8mje9HRNKg0", "id": "UExpcFp4cDRZZ1YwcngwN3dqd3JJOEhZc3hJbnFkVHJLOC4yODlGNEE0NkRGMEEzMEQy", "snippet": {"publishedAt": "2021-11-22T15:50:52Z", "channelId": "UCtojzusGJRtRzD6vAx2DBhQ", "title": "Private video", "description": "This video is private.", "thumbnails": {}, "channelTitle": "게으른 이치미 [호쇼 마린 키리누키 ch]", "playlistId": "PLipZxp4YgV0rx07wjwrI8HYsxInqdTrK8", "position": 1, "resourceId": {"kind": "youtube#video", "videoId": "-r20dDGFdto"}}, "contentDetails": {"videoId": "-r20dDGFdto"}}, {"kind": "youtube#playlistItem", "etag": "z6hBvoE0vIx54KKIRqalxWZxrSU", "id": "UExpcFp4cDRZZ1YwcngwN3dqd3JJOEhZc3hJbnFkVHJLOC4wMTcyMDhGQUE4NTIzM0Y5", "snippet": {"publishedAt": "2021-11-24T13:05:35Z", "channelId": "UCtojzusGJRtRzD6vAx2DBhQ", "title": "Private video", "description": "This video is private.", "thumbnails": {}, "channelTitle": "게으른 이치미 [호쇼 마린 키리누키 ch]", "playlistId": "PLipZxp4YgV0rx07wjwrI8HYsxInqdTrK8", "position": 2, "resourceId": {"kind": "youtube#video", "videoId": "ScKC1XFm8kE"}}, "contentDetails": {"videoId": "ScKC1XFm8kE"}}, {"kind": "youtube#playlistItem", "etag": "TENPGPnsl9uB-JPbhQmAAUx3yOk", "id": "UExpcFp4cDRZZ1YwcngwN3dqd3JJOEhZc3hJbnFkVHJLOC41MjE1MkI0OTQ2QzJGNzNG", "snippet": {"publishedAt": "2021-11-25T14:00:28Z", "channelId": "UCtojzusGJRtRzD6vAx2DBhQ", "title": "선장의 다이어트 방법", "description": "3기생 라이브는 돈없어서 무료까지만 보고 한맺혀서 편집했습니다\n\n번역 연습이라 오역이 있을 수 있습니다. 고쳐야 할 부분 알려주신다면 감사하겠습니다.\n\n원본\n【＃ぺこマリ1ブロック】ガストが出たら即終了！もっと拠点を広々にする！【ホロライブ/宝鐘マリン】\nhttps://www.youtube.com/watch?v=O9WMGcmYTtw\n마린선장님 채널 : https://www.youtube.com/channel/UCCzUftO8KOVkV4wQG1vkUvg", "thumbnails": {"default": {"url": "https://i.ytimg.com/vi/eKLmfAjUeCQ/default.jpg", "width": 120, "height": 90}, "medium": {"url": "https://i.ytimg.com/vi/eKLmfAjUeCQ/mqdefault.jpg", "width": 320, "height": 180}, "high": {"url": "https://i.ytimg.com/vi/eKLmfAjUeCQ/hqdefault.jpg", "width": 480, "height": 360}, "standard": {"url": "https://i.ytimg.com/vi/eKLmfAjUeCQ/sddefault.jpg", "width": 640, "height": 480}, "maxres": {"url": "https://i.ytimg.com/vi/eKLmfAjUeCQ/maxresdefault.jpg", "width": 1280, "height": 720}}, "channelTitle": "게으른 이치미 [호쇼 마린 키리누키 ch]", "playlistId": "PLipZxp4YgV0rx07wjwrI8HYsxInqdTrK8", "position": 3, "resourceId": {"kind": "youtube#video", "videoId": "eKLmfAjUeCQ"}, "videoOwnerChannelTitle": "게으른 이치미 [호쇼 마린 키리누키 ch]", "videoOwnerChannelId": "UCtojzusGJRtRzD6vAx2DBhQ"}, "contentDetails": {"videoId": "eKLmfAjUeCQ", "videoPublishedAt": "2021-11-25T14:01:40Z"}}, {"kind": "youtube#playlistItem", "etag": "WcDqaHar4USENKuMTb4ZsUKCboE", "id": "UExpcFp4cDRZZ1YwcngwN3dqd3JJOEhZc3hJbnFkVHJLOC4wOTA3OTZBNzVEMTUzOTMy", "snippet": {"publishedAt": "2021-11-26T13:00:14Z", "channelId": "UCtojzusGJRtRzD6vAx2DBhQ", "title": "선장님이 바다라고 하면 바다지", "description": "번역 연습이라 오역이 있을 수 있습니다. 고쳐야 할 부분 알려주신다면 감사하겠습니다.\n\n원본\n【＃ぺこマリ1ブロック】ガストが出たら即終了！もっと拠点を広々にする！【ホロライブ/宝鐘マリン】\nhttps://www.youtube.com/watch?v=O9WMGcmYTtw\n마린 채널 : https://www.youtube.com/channel/UCCzUftO8KOVkV4wQG1vkUvg", "thumbnails": {"default": {"url": "https://i.ytimg.com/vi/zi5ma4IS4LA/default.jpg", "width": 120, "height": 90}, "medium": {"url": "https://i.ytimg.com/vi/zi5ma4IS4LA/mqdefault.jpg", "width": 320, "height": 180}, "high": {"url": "https://i.ytimg.com/vi/zi5ma4IS4LA/hqdefault.jpg", "width": 480, "height": 360}, "standard": {"url": "https://i.ytimg.com/vi/zi5ma4IS4LA/sddefault.jpg", "width": 640, "height": 480}, "maxres": {"url": "https://i.ytimg.com/vi/zi5ma4IS4LA/maxresdefault.jpg", "width": 1280, "height": 720}}, "channelTitle": "게으른 이치미 [호쇼 마린 키리누키 ch]", "playlistId": "PLipZxp4YgV0rx07wjwrI8HYsxInqdTrK8", "position": 4, "resourceId": {"kind": "youtube#video", "videoId": "zi5ma4IS4LA"}, "videoOwnerChannelTitle": "게으른 이치미 [호쇼 마린 키리누키 ch]", "videoOwnerChannelId": "UCtojzusGJRtRzD6vAx2DBhQ"}, "contentDetails": {"videoId": "zi5ma4IS4LA", "videoPublishedAt": "2021-11-26T13:01:06Z"}}, {"kind": "youtube#playlistItem", "etag": "UlRGImdRzL1xJItrbNzFzi1zsHE", "id": "UExpcFp4cDRZZ1YwcngwN3dqd3JJOEhZc3hJbnFkVHJLOC4xMkVGQjNCMUM1N0RFNEUx", "snippet": {"publishedAt": "2021-12-05T18:00:37Z", "channelId": "UCtojzusGJRtRzD6vAx2DBhQ", "title": "이치미에게 태어난 의미를 부여해주는 선장", "description": "번역 연습이라 오역이 있을 수 있습니다. 고쳐야 할 부분 알려주신다면 감사하겠습니다.\n\n원본 제목 : 【#ぺこマリ1ブロック】そして船長にできるコト―――。【ホロライブ/宝鐘マリン】\n원본 링크 : https://www.youtube.com/watch?v=PHp6j4lZ_3A\n마린 채널 : https://www.youtube.com/channel/UCCzUftO8KOVkV4wQG1vkUvg", "thumbnails": {"default": {"url": "https://i.ytimg.com/vi/ihJWKNrESao/default.jpg", "width": 120, "height": 90}, "medium": {"url": "https://i.ytimg.com/vi/ihJWKNrESao/mqdefault.jpg", "width": 320, "height": 180}, "high": {"url": "https://i.ytimg.com/vi/ihJWKNrESao/hqdefault.jpg", "width": 480, "height": 360}, "standard": {"url": "https://i.ytimg.com/vi/ihJWKNrESao/sddefault.jpg", "width": 640, "height": 480}, "maxres": {"url": "https://i.ytimg.com/vi/ihJWKNrESao/maxresdefault.jpg", "width": 1280, "height": 720}}, "channelTitle": "게으른 이치미 [호쇼 마린 키리누키 ch]", "playlistId": "PLipZxp4YgV0rx07wjwrI8HYsxInqdTrK8", "position": 5, "resourceId": {"kind": "youtube#video", "videoId": "ihJWKNrESao"}, "videoOwnerChannelTitle": "게으른 이치미 [호쇼 마린 키리누키 ch]", "videoOwnerChannelId": "UCtojzusGJRtRzD6vAx2DBhQ"}, "contentDetails": {"videoId": "ihJWKNrESao", "videoPublishedAt": "2021-12-05T18:00:40Z"}}, {"kind": "youtube#playlistItem", "etag": "LqCxxTtWEn8jAHpLPKuxxX6SPqA", "id": "UExpcFp4cDRZZ1YwcngwN3dqd3JJOEhZc3hJbnFkVHJLOC41MzJCQjBCNDIyRkJDN0VD", "snippet": {"publishedAt": "2022-03-14T16:45:29Z", "channelId": "UCtojzusGJRtRzD6vAx2DBhQ", "title": "마리루이는... 존재한다!!!", "description": "번역 연습이라 오역이 있을 수 있습니다. 고쳐야 할 부분 알려주신다면 감사하겠습니다.\n\n원본 제목 : 【#りっちしょこら】今回のゲストはマリン様⚡ルイ様とビーフストロガノフ作る！【ホロライブ/癒月ちょこ/鷹嶺ルイ/宝鐘マリン】\n원본링크 : https://www.youtube.com/watch?v=YeiJnvJWVgw\n마린 채널 : https://www.youtube.com/channel/UCCzUftO8KOVkV4wQG1vkUvg", "thumbnails": {"default": {"url": "https://i.ytimg.com/vi/uikeB2yhY7E/default.jpg", "width": 120, "height": 90}, "medium": {"url": "https://i.ytimg.com/vi/uikeB2yhY7E/mqdefault.jpg", "width": 320, "height": 180}, "high": {"url": "https://i.ytimg.com/vi/uikeB2yhY7E/hqdefault.jpg", "width": 480, "height": 360}, "standard": {"url": "https://i.ytimg.com/vi/uikeB2yhY7E/sddefault.jpg", "width": 640, "height": 480}, "maxres": {"url": "https://i.ytimg.com/vi/uikeB2yhY7E/maxresdefault.jpg", "width": 1280, "height": 720}}, "channelTitle": "게으른 이치미 [호쇼 마린 키리누키 ch]", "playlistId": "PLipZxp4YgV0rx07wjwrI8HYsxInqdTrK8", "position": 6, "resourceId": {"kind": "youtube#video", "videoId": "uikeB2yhY7E"}, "videoOwnerChannelTitle": "게으른 이치미 [호쇼 마린 키리누키 ch]", "videoOwnerChannelId": "UCtojzusGJRtRzD6vAx2DBhQ"}, "contentDetails": {"videoId": "uikeB2yhY7E", "videoPublishedAt": "2022-03-14T16:39:52Z"}}, {"kind": "youtube#playlistItem", "etag": "lunlNPaK5UYsDBIvhTCje4N2nts", "id": "UExpcFp4cDRZZ1YwcngwN3dqd3JJOEhZc3hJbnFkVHJLOC5DQUNERDQ2NkIzRUQxNTY1", "snippet": {"publishedAt": "2022-03-31T17:53:16Z", "channelId": "UCtojzusGJRtRzD6vAx2DBhQ", "title": "페코라가 사장이라니.... 회사 그만둡니다", "description": "번역 연습이라 오역이 있을 수 있습니다. 고쳐야 할 부분 알려주신다면 감사하겠습니다.\n\n원본 제목 : 【新番組2】ぺこにゅーす｜PekoNews!!!ぺこ！【ホロライブ/兎田ぺこら】\n원본 링크 : https://www.youtube.com/watch?v=qzRRvb8v8mE&t=0s\n마린 채널 : https://www.youtube.com/channel/UCCzUftO8KOVkV4wQG1vkUvg", "thumbnails": {"default": {"url": "https://i.ytimg.com/vi/eMeaEl3v7OM/default.jpg", "width": 120, "height": 90}, "medium": {"url": "https://i.ytimg.com/vi/eMeaEl3v7OM/mqdefault.jpg", "width": 320, "height": 180}, "high": {"url": "https://i.ytimg.com/vi/eMeaEl3v7OM/hqdefault.jpg", "width": 480, "height": 360}}, "channelTitle": "게으른 이치미 [호쇼 마린 키리누키 ch]", "playlistId": "PLipZxp4YgV0rx07wjwrI8HYsxInqdTrK8", "position": 7, "resourceId": {"kind": "youtube#video", "videoId": "eMeaEl3v7OM"}, "videoOwnerChannelTitle": "게으른 이치미 [호쇼 마린 키리누키 ch]", "videoOwnerChannelId": "UCtojzusGJRtRzD6vAx2DBhQ"}, "contentDetails": {"videoId": "eMeaEl3v7OM", "videoPublishedAt": "2022-03-31T17:53:53Z"}}, {"kind": "youtube#playlistItem", "etag": "e_MDrVxiE0E5Ef32XcBxSmcq-lQ", "id": "UExpcFp4cDRZZ1YwcngwN3dqd3JJOEhZc3hJbnFkVHJLOC45NDk1REZENzhEMzU5MDQz", "snippet": {"publishedAt": "2022-04-06T09:41:19Z", "channelId": "UCtojzusGJRtRzD6vAx2DBhQ", "title": "선장님이 랩하는 거 들어봤어?", "description": "번역 연습이라 오역이 있을 수 있습니다. 고쳐야 할 부분 알려주신다면 감사하겠습니다.\n\n원본 제목 : 【BIRTHDAY COUNT-DOWN】Calling My Friends and Chilling!\n원본링크 : https://www.youtube.com/watch?v=WcvGVVwIRfk&t=5507s\n마린 채널 : https://www.youtube.com/channel/UCCzUftO8KOVkV4wQG1vkUvg\n\n원래는 마린 도츠부분 다 할려고 했는데 영어가 고통스러워서 랩만 올립니다", "thumbnails": {"default": {"url": "https://i.ytimg.com/vi/xvQ6ai-HLdc/default.jpg", "width": 120, "height": 90}, "medium": {"url": "https://i.ytimg.com/vi/xvQ6ai-HLdc/mqdefault.jpg", "width": 320, "height": 180}, "high": {"url": "https://i.ytimg.com/vi/xvQ6ai-HLdc/hqdefault.jpg", "width": 480, "height": 360}, "standard": {"url": "https://i.ytimg.com/vi/xvQ6ai-HLdc/sddefault.jpg", "width": 640, "height": 480}, "maxres": {"url": "https://i.ytimg.com/vi/xvQ6ai-HLdc/maxresdefault.jpg", "width": 1280, "height": 720}}, "channelTitle": "게으른 이치미 [호쇼 마린 키리누키 ch]", "playlistId": "PLipZxp4YgV0rx07wjwrI8HYsxInqdTrK8", "position": 8, "resourceId": {"kind": "youtube#video", "videoId": "xvQ6ai-HLdc"}, "videoOwnerChannelTitle": "게으른 이치미 [호쇼 마린 키리누키 ch]", "videoOwnerChannelId": "UCtojzusGJRtRzD6vAx2DBhQ"}, "contentDetails": {"videoId": "xvQ6ai-HLdc", "videoPublishedAt": "2022-04-06T09:42:18Z"}}, {"kind": "youtube#playlistItem", "etag": "fIW-tivBXT-2IqYVaGfLJSwqW7U", "id": "UExpcFp4cDRZZ1YwcngwN3dqd3JJOEhZc3hJbnFkVHJLOC5GNjNDRDREMDQxOThCMDQ2", "snippet": {"publishedAt": "2022-04-06T14:47:46Z", "channelId": "UCtojzusGJRtRzD6vAx2DBhQ", "title": "신곡 영상 그래서 언제 올라옴?", "description": "번역 연습이라 오역이 있을 수 있습니다. 고쳐야 할 부분 알려주신다면 감사하겠습니다.\n\n원본 제목 : キミたち～♡【ホロライブ/宝鐘マリン】\n원본 링크 : https://www.youtube.com/watch?v=qhCHbdIayIY\n마린 채널 : https://www.youtube.com/channel/UCCzUftO8KOVkV4wQG1vkUvg", "thumbnails": {"default": {"url": "https://i.ytimg.com/vi/3QJJkU3HKP0/default.jpg", "width": 120, "height": 90}, "medium": {"url": "https://i.ytimg.com/vi/3QJJkU3HKP0/mqdefault.jpg", "width": 320, "height": 180}, "high": {"url": "https://i.ytimg.com/vi/3QJJkU3HKP0/hqdefault.jpg", "width": 480, "height": 360}, "standard": {"url": "https://i.ytimg.com/vi/3QJJkU3HKP0/sddefault.jpg", "width": 640, "height": 480}, "maxres": {"url": "https://i.ytimg.com/vi/3QJJkU3HKP0/maxresdefault.jpg", "width": 1280, "height": 720}}, "channelTitle": "게으른 이치미 [호쇼 마린 키리누키 ch]", "playlistId": "PLipZxp4YgV0rx07wjwrI8HYsxInqdTrK8", "position": 9, "resourceId": {"kind": "youtube#video", "videoId": "3QJJkU3HKP0"}, "videoOwnerChannelTitle": "게으른 이치미 [호쇼 마린 키리누키 ch]", "videoOwnerChannelId": "UCtojzusGJRtRzD6vAx2DBhQ"}, "contentDetails": {"videoId": "3QJJkU3HKP0", "videoPublishedAt": "2022-04-04T07:03:53Z"}}, {"kind": "youtube#playlistItem", "etag": "lnLMwOHwjyhsCJLUuU6rOpf8WOs", "id": "UExpcFp4cDRZZ1YwcngwN3dqd3JJOEhZc3hJbnFkVHJLOC40NzZCMERDMjVEN0RFRThB", "snippet": {"publishedAt": "2022-04-06T14:49:12Z", "channelId": "UCtojzusGJRtRzD6vAx2DBhQ", "title": "순수하게 부탁합니다. 지퍼 올렸다내렸다 해주세요.", "description": "번역 연습이라 오역이 있을 수 있습니다. 고쳐야 할 부분 알려주신다면 감사하겠습니다.\n\n원본 제목 : 【#ぺこマリ1ブロック】そして船長にできるコト―――。【ホロライブ/宝鐘マリン】\n원본 링크 : https://www.youtube.com/watch?v=PHp6j4lZ_3A\n마린 채널 : https://www.youtube.com/channel/UCCzUftO8KOVkV4wQG1vkUvg", "thumbnails": {"default": {"url": "https://i.ytimg.com/vi/kpI2UJu7SXQ/default.jpg", "width": 120, "height": 90}, "medium": {"url": "https://i.ytimg.com/vi/kpI2UJu7SXQ/mqdefault.jpg", "width": 320, "height": 180}, "high": {"url": "https://i.ytimg.com/vi/kpI2UJu7SXQ/hqdefault.jpg", "width": 480, "height": 360}, "standard": {"url": "https://i.ytimg.com/vi/kpI2UJu7SXQ/sddefault.jpg", "width": 640, "height": 480}, "maxres": {"url": "https://i.ytimg.com/vi/kpI2UJu7SXQ/maxresdefault.jpg", "width": 1280, "height": 720}}, "channelTitle": "게으른 이치미 [호쇼 마린 키리누키 ch]", "playlistId": "PLipZxp4YgV0rx07wjwrI8HYsxInqdTrK8", "position": 10, "resourceId": {"kind": "youtube#video", "videoId": "kpI2UJu7SXQ"}, "videoOwnerChannelTitle": "게으른 이치미 [호쇼 마린 키리누키 ch]", "videoOwnerChannelId": "UCtojzusGJRtRzD6vAx2DBhQ"}, "contentDetails": {"videoId": "kpI2UJu7SXQ", "videoPublishedAt": "2021-12-05T18:02:28Z"}}, {"kind": "youtube#playlistItem", "etag": "Lpp6ptME9dpWFuwQNjSk4V3IF6k", "id": "UExpcFp4cDRZZ1YwcngwN3dqd3JJOEhZc3hJbnFkVHJLOC5EMEEwRUY5M0RDRTU3NDJC", "snippet": {"publishedAt": "2022-04-06T14:49:21Z", "channelId": "UCtojzusGJRtRzD6vAx2DBhQ", "title": "개인적으로 볼려고 딴 키리누키", "description": "번역 연습이라 오역이 있을 수 있습니다. 고쳐야 할 부분 알려주신다면 감사하겠습니다.\n\n원본 제목 : 【#ぺこマリ1ブロック】そして船長にできるコト―――。【ホロライブ/宝鐘マリン】\n원본 링크 : https://www.youtube.com/watch?v=PHp6j4lZ_3A\n마린 채널 : https://www.youtube.com/channel/UCCzUftO8KOVkV4wQG1vkUvg", "thumbnails": {"default": {"url": "https://i.ytimg.com/vi/eO8V-VWjU5Y/default.jpg", "width": 120, "height": 90}, "medium": {"url": "https://i.ytimg.com/vi/eO8V-VWjU5Y/mqdefault.jpg", "width": 320, "height": 180}, "high": {"url": "https://i.ytimg.com/vi/eO8V-VWjU5Y/hqdefault.jpg", "width": 480, "height": 360}, "standard": {"url": "https://i.ytimg.com/vi/eO8V-VWjU5Y/sddefault.jpg", "width": 640, "height": 480}, "maxres": {"url": "https://i.ytimg.com/vi/eO8V-VWjU5Y/maxresdefault.jpg", "width": 1280, "height": 720}}, "channelTitle": "게으른 이치미 [호쇼 마린 키리누키 ch]", "playlistId": "PLipZxp4YgV0rx07wjwrI8HYsxInqdTrK8", "position": 11, "resourceId": {"kind": "youtube#video", "videoId": "eO8V-VWjU5Y"}, "videoOwnerChannelTitle": "게으른 이치미 [호쇼 마린 키리누키 ch]", "videoOwnerChannelId": "UCtojzusGJRtRzD6vAx2DBhQ"}, "contentDetails": {"videoId": "eO8V-VWjU5Y", "videoPublishedAt": "2021-12-05T17:58:56Z"}}, {"kind": "youtube#playlistItem", "etag": "ULzhlA3oF0ym5wL5LmYGlc0Np1I", "id": "UExpcFp4cDRZZ1YwcngwN3dqd3JJOEhZc3hJbnFkVHJLOC45ODRDNTg0QjA4NkFBNkQy", "snippet": {"publishedAt": "2022-04-13T06:54:32Z", "channelId": "UCtojzusGJRtRzD6vAx2DBhQ", "title": "에로라이브를 향해 출항이다!!!!!!", "description": "번역 연습이라 오역이 있을 수 있습니다. 고쳐야 할 부분 알려주신다면 감사하겠습니다.\n\n원본 제목 : 【#ホロGarticPhone】ホロの画伯たちでお絵かき伝言やるぞやるぞ【ホロライブ/宝鐘マリン】\n원본링크 : https://www.youtube.com/watch?v=0SfUNfAg1cM\n마린 채널 : https://www.youtube.com/channel/UCCzUftO8KOVkV4wQG1vkUvg\\\n\n이후 선장님은 코로나에 걸리셔서 현재 휴식기간에 들어갔습니다. 그래서 한동안 영상이 없을 듯 합니다 ㅎㅎ", "thumbnails": {"default": {"url": "https://i.ytimg.com/vi/y2hb-VJf9JA/default.jpg", "width": 120, "height": 90}, "medium": {"url": "https://i.ytimg.com/vi/y2hb-VJf9JA/mqdefault.jpg", "width": 320, "height": 180}, "high": {"url": "https://i.ytimg.com/vi/y2hb-VJf9JA/hqdefault.jpg", "width": 480, "height": 360}}, "channelTitle": "게으른 이치미 [호쇼 마린 키리누키 ch]", "playlistId": "PLipZxp4YgV0rx07wjwrI8HYsxInqdTrK8", "position": 12, "resourceId": {"kind": "youtube#video", "videoId": "y2hb-VJf9JA"}, "videoOwnerChannelTitle": "게으른 이치미 [호쇼 마린 키리누키 ch]", "videoOwnerChannelId": "UCtojzusGJRtRzD6vAx2DBhQ"}, "contentDetails": {"videoId": "y2hb-VJf9JA", "videoPublishedAt": "2022-04-13T06:56:34Z"}}, {"kind": "youtube#playlistItem", "etag": "BfpvNbX0pZXUSg3RpCXMKIpQl2Q", "id": "UExpcFp4cDRZZ1YwcngwN3dqd3JJOEhZc3hJbnFkVHJLOC4zMDg5MkQ5MEVDMEM1NTg2", "snippet": {"publishedAt": "2022-04-18T11:45:11Z", "channelId": "UCtojzusGJRtRzD6vAx2DBhQ", "title": "선장 자리를 노리는 타카네 루이", "description": "번역 연습이라 오역이 있을 수 있습니다. 고쳐야 할 부분 알려주신다면 감사하겠습니다.\n\n원본 제목 : 【#マリルイ】鷹嶺ルイ...好きなんだろ？【ホロライブ/宝鐘マリン】\n원본 링크 : https://www.youtube.com/watch?v=YLjiWJv6lhA\n마린 채널 : https://www.youtube.com/channel/UCCzUftO8KOVkV4wQG1vkUvg\n\n오랬동안 안올리면 양심에 찔려서 올린거지 절대로 시험기간인데 시험공부 하기 귀찮아서 올린게 아님\n암튼 아님", "thumbnails": {"default": {"url": "https://i.ytimg.com/vi/8qeEdJvVVzk/default.jpg", "width": 120, "height": 90}, "medium": {"url": "https://i.ytimg.com/vi/8qeEdJvVVzk/mqdefault.jpg", "width": 320, "height": 180}, "high": {"url": "https://i.ytimg.com/vi/8qeEdJvVVzk/hqdefault.jpg", "width": 480, "height": 360}, "standard": {"url": "https://i.ytimg.com/vi/8qeEdJvVVzk/sddefault.jpg", "width": 640, "height": 480}, "maxres": {"url": "https://i.ytimg.com/vi/8qeEdJvVVzk/maxresdefault.jpg", "width": 1280, "height": 720}}, "channelTitle": "게으른 이치미 [호쇼 마린 키리누키 ch]", "playlistId": "PLipZxp4YgV0rx07wjwrI8HYsxInqdTrK8", "position": 13, "resourceId": {"kind": "youtube#video", "videoId": "8qeEdJvVVzk"}, "videoOwnerChannelTitle": "게으른 이치미 [호쇼 마린 키리누키 ch]", "videoOwnerChannelId": "UCtojzusGJRtRzD6vAx2DBhQ"}, "contentDetails": {"videoId": "8qeEdJvVVzk", "videoPublishedAt": "2022-04-18T11:46:36Z"}}, {"kind": "youtube#playlistItem", "etag": "zGh36UKFurBSnzLSPx6lORwHOl0", "id": "UExpcFp4cDRZZ1YwcngwN3dqd3JJOEhZc3hJbnFkVHJLOC41Mzk2QTAxMTkzNDk4MDhF", "snippet": {"publishedAt": "2022-04-20T18:39:25Z", "channelId": "UCtojzusGJRtRzD6vAx2DBhQ", "title": "칸나가 귀여운 선장님", "description": "번역 연습이라 오역이 있을 수 있습니다. 고쳐야 할 부분 알려주신다면 감사하겠습니다.\n\n원본 제목 : 【小林さんちのメイドラゴン】え！？！？弾幕シューティングですか！？【ホロライブ/宝鐘マリン】\n원본 링크 : https://www.youtube.com/watch?v=kYCw4r16V3I\n마린 채널 : https://www.youtube.com/channel/UCCzUftO8KOVkV4wQG1vkUvg", "thumbnails": {"default": {"url": "https://i.ytimg.com/vi/HkSknY4pQzU/default.jpg", "width": 120, "height": 90}, "medium": {"url": "https://i.ytimg.com/vi/HkSknY4pQzU/mqdefault.jpg", "width": 320, "height": 180}, "high": {"url": "https://i.ytimg.com/vi/HkSknY4pQzU/hqdefault.jpg", "width": 480, "height": 360}, "standard": {"url": "https://i.ytimg.com/vi/HkSknY4pQzU/sddefault.jpg", "width": 640, "height": 480}, "maxres": {"url": "https://i.ytimg.com/vi/HkSknY4pQzU/maxresdefault.jpg", "width": 1280, "height": 720}}, "channelTitle": "게으른 이치미 [호쇼 마린 키리누키 ch]", "playlistId": "PLipZxp4YgV0rx07wjwrI8HYsxInqdTrK8", "position": 14, "resourceId": {"kind": "youtube#video", "videoId": "HkSknY4pQzU"}, "videoOwnerChannelTitle": "게으른 이치미 [호쇼 마린 키리누키 ch]", "videoOwnerChannelId": "UCtojzusGJRtRzD6vAx2DBhQ"}, "contentDetails": {"videoId": "HkSknY4pQzU", "videoPublishedAt": "2022-04-20T18:39:58Z"}}], "pageInfo": {"totalResults": 220, "resultsPerPage": 15}}}