{"kind": "youtube#playlistListResponse", "etag": "ht0orqxfczdt5dXQ_ktotr6mY_A", "pageInfo": {"totalResults": 1, "resultsPerPage": 20}, "items": [{"kind": "youtube#playlist", "etag": "f68hrxSHO4IXSjCkrDgR-BSIWDo", "id": "PLFIFptugLG7EIT3Fhow1xu8Ajzzdddkd7", "snippet": {"publishedAt": "2023-07-09T03:37:41Z", "channelId": "UCt5iWySH47xZqrbSHV0uvkQ", "title": "샤로우 30분 BGM 모음", "description": "", "thumbnails": {"default": {"url": "https://i.ytimg.com/vi/HWsOivtPz-o/default.jpg", "width": 120, "height": 90}, "medium": {"url": "https://i.ytimg.com/vi/HWsOivtPz-o/mqdefault.jpg", "width": 320, "height": 180}, "high": {"url": "https://i.ytimg.com/vi/HWsOivtPz-o/hqdefault.jpg", "width": 480, "height": 360}, "standard": {"url": "https://i.ytimg.com/vi/HWsOivtPz-o/sddefault.jpg", "width": 640, "height": 480}, "maxres": {"url": "https://i.ytimg.com/vi/HWsOivtPz-o/maxresdefault.jpg", "width": 1280, "height": 720}}, "channelTitle": "홀로그레이스", "localized": {"title": "샤로우 30분 BGM 모음", "description": ""}}, "contentDetails": {"itemCount": 21}}]}