{"kind": "youtube#playlistListResponse", "etag": "8W37d7k3fLtRA8Kyt2Rkgr_RIZU", "pageInfo": {"totalResults": 5, "resultsPerPage": 20}, "items": [{"kind": "youtube#playlist", "etag": "24sbMEQOk50aHn2QbD1bujDo8ss", "id": "PLs0Q2dF0Ql3xS_-rnpPo9DEjGsgNrfWyO", "snippet": {"publishedAt": "2023-07-22T05:46:36Z", "channelId": "UC1H-AidgZxdmlNK0Qe0K0Cw", "title": "수출에서 활약하는 한국산 무기", "description": "", "thumbnails": {"default": {"url": "https://i.ytimg.com/img/no_thumbnail.jpg", "width": 120, "height": 90}, "medium": {"url": "https://i.ytimg.com/img/no_thumbnail.jpg", "width": 320, "height": 180}, "high": {"url": "https://i.ytimg.com/img/no_thumbnail.jpg", "width": 480, "height": 360}}, "channelTitle": "채리튜브", "localized": {"title": "수출에서 활약하는 한국산 무기", "description": ""}}, "contentDetails": {"itemCount": 0}}, {"kind": "youtube#playlist", "etag": "tM5iQmqugR0fWRHB4I7r0nKSIYA", "id": "PLs0Q2dF0Ql3x5yikkHqCjAq3dXm1I5_TY", "snippet": {"publishedAt": "2023-07-22T05:45:20Z", "channelId": "UC1H-AidgZxdmlNK0Qe0K0Cw", "title": "개발중인 강력한 무기", "description": "", "thumbnails": {"default": {"url": "https://i.ytimg.com/vi/4PQFxZb1CUE/default.jpg", "width": 120, "height": 90}, "medium": {"url": "https://i.ytimg.com/vi/4PQFxZb1CUE/mqdefault.jpg", "width": 320, "height": 180}, "high": {"url": "https://i.ytimg.com/vi/4PQFxZb1CUE/hqdefault.jpg", "width": 480, "height": 360}, "standard": {"url": "https://i.ytimg.com/vi/4PQFxZb1CUE/sddefault.jpg", "width": 640, "height": 480}, "maxres": {"url": "https://i.ytimg.com/vi/4PQFxZb1CUE/maxresdefault.jpg", "width": 1280, "height": 720}}, "channelTitle": "채리튜브", "localized": {"title": "개발중인 강력한 무기", "description": ""}}, "contentDetails": {"itemCount": 2}}, {"kind": "youtube#playlist", "etag": "_5hRrK3Rl99rBA9XItzV-Xp-KRo", "id": "PLs0Q2dF0Ql3wCy8snU-SgVuh0RcQpjcX2", "snippet": {"publishedAt": "2023-07-22T05:44:16Z", "channelId": "UC1H-AidgZxdmlNK0Qe0K0Cw", "title": "자랑스런 대한민국", "description": "", "thumbnails": {"default": {"url": "https://i.ytimg.com/vi/IM2pmnEhFt8/default.jpg", "width": 120, "height": 90}, "medium": {"url": "https://i.ytimg.com/vi/IM2pmnEhFt8/mqdefault.jpg", "width": 320, "height": 180}, "high": {"url": "https://i.ytimg.com/vi/IM2pmnEhFt8/hqdefault.jpg", "width": 480, "height": 360}, "standard": {"url": "https://i.ytimg.com/vi/IM2pmnEhFt8/sddefault.jpg", "width": 640, "height": 480}, "maxres": {"url": "https://i.ytimg.com/vi/IM2pmnEhFt8/maxresdefault.jpg", "width": 1280, "height": 720}}, "channelTitle": "채리튜브", "localized": {"title": "자랑스런 대한민국", "description": ""}}, "contentDetails": {"itemCount": 5}}, {"kind": "youtube#playlist", "etag": "L6xTw3f1FhOIX7OwnQazVRrpEMs", "id": "PLs0Q2dF0Ql3xZruqUU4nB90Vo9WERpP3H", "snippet": {"publishedAt": "2023-07-22T05:40:30Z", "channelId": "UC1H-AidgZxdmlNK0Qe0K0Cw", "title": "한국의 위력적인 군사력", "description": "", "thumbnails": {"default": {"url": "https://i.ytimg.com/vi/Uffe1WL_F30/default.jpg", "width": 120, "height": 90}, "medium": {"url": "https://i.ytimg.com/vi/Uffe1WL_F30/mqdefault.jpg", "width": 320, "height": 180}, "high": {"url": "https://i.ytimg.com/vi/Uffe1WL_F30/hqdefault.jpg", "width": 480, "height": 360}, "standard": {"url": "https://i.ytimg.com/vi/Uffe1WL_F30/sddefault.jpg", "width": 640, "height": 480}, "maxres": {"url": "https://i.ytimg.com/vi/Uffe1WL_F30/maxresdefault.jpg", "width": 1280, "height": 720}}, "channelTitle": "채리튜브", "localized": {"title": "한국의 위력적인 군사력", "description": ""}}, "contentDetails": {"itemCount": 3}}, {"kind": "youtube#playlist", "etag": "bjN3lqVmXm2Q606vlthS5PZRbUQ", "id": "PLs0Q2dF0Ql3yNf7ITTSjN8zsBfKulguoq", "snippet": {"publishedAt": "2021-10-26T08:05:16Z", "channelId": "UC1H-AidgZxdmlNK0Qe0K0Cw", "title": "강력한 국산 무기", "description": "", "thumbnails": {"default": {"url": "https://i.ytimg.com/vi/QhIqRhlnkLM/default.jpg", "width": 120, "height": 90}, "medium": {"url": "https://i.ytimg.com/vi/QhIqRhlnkLM/mqdefault.jpg", "width": 320, "height": 180}, "high": {"url": "https://i.ytimg.com/vi/QhIqRhlnkLM/hqdefault.jpg", "width": 480, "height": 360}, "standard": {"url": "https://i.ytimg.com/vi/QhIqRhlnkLM/sddefault.jpg", "width": 640, "height": 480}, "maxres": {"url": "https://i.ytimg.com/vi/QhIqRhlnkLM/maxresdefault.jpg", "width": 1280, "height": 720}}, "channelTitle": "채리튜브", "localized": {"title": "강력한 국산 무기", "description": ""}}, "contentDetails": {"itemCount": 6}}]}