{"kind": "youtube#playlistListResponse", "etag": "Aiwojvk57D_pP2_7oBS9rda2-Ig", "pageInfo": {"totalResults": 3, "resultsPerPage": 20}, "items": [{"kind": "youtube#playlist", "etag": "wSsuUnLZJCOkca_QXtnsZpwfybE", "id": "PLwo7f3uF3c7nT6GtoF0ykT0r5xeNfprje", "snippet": {"publishedAt": "2019-11-18T05:27:22Z", "channelId": "UCRytxwcg5ROIFlkDy6cozFQ", "title": "[북부의 왕] 주성치 영화 병맛리뷰", "description": "북부의 왕 스타일로 리뷰한 주성치 코미디!", "thumbnails": {"default": {"url": "https://i.ytimg.com/vi/wxv2aYDvXNU/default.jpg", "width": 120, "height": 90}, "medium": {"url": "https://i.ytimg.com/vi/wxv2aYDvXNU/mqdefault.jpg", "width": 320, "height": 180}, "high": {"url": "https://i.ytimg.com/vi/wxv2aYDvXNU/hqdefault.jpg", "width": 480, "height": 360}, "standard": {"url": "https://i.ytimg.com/vi/wxv2aYDvXNU/sddefault.jpg", "width": 640, "height": 480}, "maxres": {"url": "https://i.ytimg.com/vi/wxv2aYDvXNU/maxresdefault.jpg", "width": 1280, "height": 720}}, "channelTitle": "북부의 왕 Movie Review", "localized": {"title": "[북부의 왕] 주성치 영화 병맛리뷰", "description": "북부의 왕 스타일로 리뷰한 주성치 코미디!"}}, "contentDetails": {"itemCount": 5}}, {"kind": "youtube#playlist", "etag": "Nf2e8zTIQWDX-F97bHk3sfUwAyk", "id": "PLwo7f3uF3c7lUnZ7b-NawELXOJBgpfMHy", "snippet": {"publishedAt": "2019-10-04T13:16:09Z", "channelId": "UCRytxwcg5ROIFlkDy6cozFQ", "title": "[북부의 왕] 병맛주의 영화리뷰", "description": "북부의 왕 추천 병맛코믹영화 모음!", "thumbnails": {"default": {"url": "https://i.ytimg.com/vi/XUhK9oNwdK4/default.jpg", "width": 120, "height": 90}, "medium": {"url": "https://i.ytimg.com/vi/XUhK9oNwdK4/mqdefault.jpg", "width": 320, "height": 180}, "high": {"url": "https://i.ytimg.com/vi/XUhK9oNwdK4/hqdefault.jpg", "width": 480, "height": 360}, "standard": {"url": "https://i.ytimg.com/vi/XUhK9oNwdK4/sddefault.jpg", "width": 640, "height": 480}, "maxres": {"url": "https://i.ytimg.com/vi/XUhK9oNwdK4/maxresdefault.jpg", "width": 1280, "height": 720}}, "channelTitle": "북부의 왕 Movie Review", "localized": {"title": "[북부의 왕] 병맛주의 영화리뷰", "description": "북부의 왕 추천 병맛코믹영화 모음!"}}, "contentDetails": {"itemCount": 43}}, {"kind": "youtube#playlist", "etag": "ppmGzlW4wDLSQckqrcvT3eldQs0", "id": "PLwo7f3uF3c7mRsxb8y53CnntJ2LplRCzD", "snippet": {"publishedAt": "2019-04-03T11:57:54Z", "channelId": "UCRytxwcg5ROIFlkDy6cozFQ", "title": "[북부의 왕] 영화리뷰", "description": "북부의 왕 추천 영화 모두보기!", "thumbnails": {"default": {"url": "https://i.ytimg.com/vi/z68GZajNNfA/default.jpg", "width": 120, "height": 90}, "medium": {"url": "https://i.ytimg.com/vi/z68GZajNNfA/mqdefault.jpg", "width": 320, "height": 180}, "high": {"url": "https://i.ytimg.com/vi/z68GZajNNfA/hqdefault.jpg", "width": 480, "height": 360}, "standard": {"url": "https://i.ytimg.com/vi/z68GZajNNfA/sddefault.jpg", "width": 640, "height": 480}, "maxres": {"url": "https://i.ytimg.com/vi/z68GZajNNfA/maxresdefault.jpg", "width": 1280, "height": 720}}, "channelTitle": "북부의 왕 Movie Review", "localized": {"title": "[북부의 왕] 영화리뷰", "description": "북부의 왕 추천 영화 모두보기!"}}, "contentDetails": {"itemCount": 75}}]}