{"자동차 케미컬 Automotive chemicals": {"error": {"code": 403, "message": "The request cannot be completed because you have exceeded your <a href=\"/youtube/v3/getting-started#quota\">quota</a>.", "errors": [{"message": "The request cannot be completed because you have exceeded your <a href=\"/youtube/v3/getting-started#quota\">quota</a>.", "domain": "youtube.quota", "reason": "quotaExceeded"}]}}, "자동차 관리 Car care": {"error": {"code": 403, "message": "The request cannot be completed because you have exceeded your <a href=\"/youtube/v3/getting-started#quota\">quota</a>.", "errors": [{"message": "The request cannot be completed because you have exceeded your <a href=\"/youtube/v3/getting-started#quota\">quota</a>.", "domain": "youtube.quota", "reason": "quotaExceeded"}]}}, "자동차 전기 Car electric": {"error": {"code": 403, "message": "The request cannot be completed because you have exceeded your <a href=\"/youtube/v3/getting-started#quota\">quota</a>.", "errors": [{"message": "The request cannot be completed because you have exceeded your <a href=\"/youtube/v3/getting-started#quota\">quota</a>.", "domain": "youtube.quota", "reason": "quotaExceeded"}]}}, "자동차 에어컨 히터 공조장치 Car air conditioner heater air conditioner": {"error": {"code": 403, "message": "The request cannot be completed because you have exceeded your <a href=\"/youtube/v3/getting-started#quota\">quota</a>.", "errors": [{"message": "The request cannot be completed because you have exceeded your <a href=\"/youtube/v3/getting-started#quota\">quota</a>.", "domain": "youtube.quota", "reason": "quotaExceeded"}]}}, "새 차 중고차 구매 가이드 New Cars Used Car Buying Guide": {"error": {"code": 403, "message": "The request cannot be completed because you have exceeded your <a href=\"/youtube/v3/getting-started#quota\">quota</a>.", "errors": [{"message": "The request cannot be completed because you have exceeded your <a href=\"/youtube/v3/getting-started#quota\">quota</a>.", "domain": "youtube.quota", "reason": "quotaExceeded"}]}}, "자동차 타이어 Car tire": {"error": {"code": 403, "message": "The request cannot be completed because you have exceeded your <a href=\"/youtube/v3/getting-started#quota\">quota</a>.", "errors": [{"message": "The request cannot be completed because you have exceeded your <a href=\"/youtube/v3/getting-started#quota\">quota</a>.", "domain": "youtube.quota", "reason": "quotaExceeded"}]}}, "자동차 정비 Car maintenance": {"error": {"code": 403, "message": "The request cannot be completed because you have exceeded your <a href=\"/youtube/v3/getting-started#quota\">quota</a>.", "errors": [{"message": "The request cannot be completed because you have exceeded your <a href=\"/youtube/v3/getting-started#quota\">quota</a>.", "domain": "youtube.quota", "reason": "quotaExceeded"}]}}, "살아가는 이야기 Living story": {"error": {"code": 403, "message": "The request cannot be completed because you have exceeded your <a href=\"/youtube/v3/getting-started#quota\">quota</a>.", "errors": [{"message": "The request cannot be completed because you have exceeded your <a href=\"/youtube/v3/getting-started#quota\">quota</a>.", "domain": "youtube.quota", "reason": "quotaExceeded"}]}}}